{
  "fiscal_year": "2568",
  "total_budget": 141700000000,
  "metadata": {
    "source": "สำนักงบประมาณ (bb.go.th) — เอกสารงบประมาณรายจ่ายประจำปีงบประมาณ พ.ศ. 2568 (ข้อมูลจำลองเพื่อการสาธิตพอร์ตโฟลิโอ ไม่ใช่ตัวเลขจริง)",
    "parsed_at": "2026-06-01T00:00:00.000Z",
    "rules_version": "v1.0-phase0"
  },
  "ministries": [
    {
      "id": "moe",
      "name": "กระทรวงศึกษาธิการ",
      "budget": 13815000000,
      "color_category": "purple",
      "departments": [
        {
          "id": "moe-001",
          "name": "สำนักงานคณะกรรมการการศึกษาขั้นพื้นฐาน",
          "budget": 11250000000,
          "projects": [
            {
              "id": "moe-001-01",
              "name": "โครงการอาหารกลางวันนักเรียนทั่วประเทศ",
              "amount": 8500000000,
              "previous_amount": 8200000000,
              "change_pct": 3.7,
              "budget_type": "operating",
              "province": "ทั่วประเทศ",
              "plan_name": "ยุทธศาสตร์ชาติด้านการพัฒนาและเสริมสร้างศักยภาพทรัพยากรมนุษย์",
              "flags": [],
              "history": [
                { "year": "2564", "amount": 7500000000 },
                { "year": "2565", "amount": 7650000000 },
                { "year": "2566", "amount": 7800000000 },
                { "year": "2567", "amount": 8200000000 },
                { "year": "2568", "amount": 8500000000 }
              ]
            },
            {
              "id": "moe-001-02",
              "name": "โครงการก่อสร้างอาคารเรียนภูมิภาค",
              "amount": 2300000000,
              "previous_amount": 1400000000,
              "change_pct": 64.3,
              "budget_type": "investment",
              "province": "เชียงใหม่",
              "plan_name": "ยุทธศาสตร์ชาติด้านการพัฒนาและเสริมสร้างศักยภาพทรัพยากรมนุษย์",
              "flags": [
                {
                  "rule": "unusual_increase",
                  "severity": "warning",
                  "label": "เพิ่มผิดปกติ",
                  "description": "งบประมาณเพิ่มขึ้น 64.3% จากปีก่อนหน้า ซึ่งเกินเกณฑ์ 50% ที่กำหนดไว้สำหรับการตรวจสอบเพิ่มเติม",
                  "statistical_context": {
                    "previous_avg_5yr": 1414000000,
                    "threshold_pct": 50
                  }
                }
              ],
              "history": [
                { "year": "2564", "amount": 1100000000 },
                { "year": "2565", "amount": 1250000000 },
                { "year": "2566", "amount": 1320000000 },
                { "year": "2567", "amount": 1400000000 },
                { "year": "2568", "amount": 2300000000 }
              ]
            },
            {
              "id": "moe-001-03",
              "name": "โครงการพัฒนาหลักสูตรดิจิทัลและสื่อการเรียนรู้ออนไลน์",
              "amount": 450000000,
              "previous_amount": 0,
              "change_pct": 0,
              "budget_type": "other",
              "province": "ทั่วประเทศ",
              "plan_name": "ยุทธศาสตร์ชาติด้านการพัฒนาและเสริมสร้างศักยภาพทรัพยากรมนุษย์",
              "flags": [],
              "history": [
                { "year": "2568", "amount": 450000000 }
              ]
            }
          ]
        },
        {
          "id": "moe-002",
          "name": "สำนักงานคณะกรรมการการอาชีวศึกษา",
          "budget": 2565000000,
          "projects": [
            {
              "id": "moe-002-01",
              "name": "โครงการจัดซื้อเครื่องมือฝึกอาชีวะขั้นสูง",
              "amount": 1850000000,
              "previous_amount": 1200000000,
              "change_pct": 54.2,
              "budget_type": "investment",
              "province": "ขอนแก่น",
              "plan_name": "ยุทธศาสตร์ชาติด้านการพัฒนาและเสริมสร้างศักยภาพทรัพยากรมนุษย์",
              "flags": [
                {
                  "rule": "unusual_increase",
                  "severity": "warning",
                  "label": "เพิ่มผิดปกติ",
                  "description": "งบประมาณเพิ่มขึ้น 54.2% จากปีก่อนหน้า ซึ่งเกินเกณฑ์ 50% ที่กำหนดไว้สำหรับการตรวจสอบเพิ่มเติม",
                  "statistical_context": {
                    "previous_avg_5yr": 1110000000,
                    "threshold_pct": 50
                  }
                }
              ],
              "history": [
                { "year": "2564", "amount": 980000000 },
                { "year": "2565", "amount": 1050000000 },
                { "year": "2566", "amount": 1120000000 },
                { "year": "2567", "amount": 1200000000 },
                { "year": "2568", "amount": 1850000000 }
              ]
            },
            {
              "id": "moe-002-02",
              "name": "โครงการพัฒนาศักยภาพครูอาชีวศึกษา",
              "amount": 620000000,
              "previous_amount": 580000000,
              "change_pct": 6.9,
              "budget_type": "personnel",
              "province": "ทั่วประเทศ",
              "plan_name": "ยุทธศาสตร์ชาติด้านการพัฒนาและเสริมสร้างศักยภาพทรัพยากรมนุษย์",
              "flags": [],
              "history": [
                { "year": "2564", "amount": 540000000 },
                { "year": "2565", "amount": 555000000 },
                { "year": "2566", "amount": 565000000 },
                { "year": "2567", "amount": 580000000 },
                { "year": "2568", "amount": 620000000 }
              ]
            },
            {
              "id": "moe-002-03",
              "name": "โครงการศูนย์ทดสอบมาตรฐานฝีมือแรงงาน",
              "amount": 95000000,
              "previous_amount": 92000000,
              "change_pct": 3.3,
              "budget_type": "operating",
              "province": "ชลบุรี",
              "plan_name": "ยุทธศาสตร์ชาติด้านการพัฒนาและเสริมสร้างศักยภาพทรัพยากรมนุษย์",
              "flags": [],
              "history": [
                { "year": "2564", "amount": 85000000 },
                { "year": "2565", "amount": 88000000 },
                { "year": "2566", "amount": 90000000 },
                { "year": "2567", "amount": 92000000 },
                { "year": "2568", "amount": 95000000 }
              ]
            }
          ]
        }
      ]
    },
    {
      "id": "moph",
      "name": "กระทรวงสาธารณสุข",
      "budget": 26530000000,
      "color_category": "teal",
      "departments": [
        {
          "id": "moph-001",
          "name": "กรมควบคุมโรค",
          "budget": 9580000000,
          "projects": [
            {
              "id": "moph-001-01",
              "name": "โครงการเฝ้าระวังและป้องกันโรคติดต่ออุบัติใหม่",
              "amount": 3200000000,
              "previous_amount": 2100000000,
              "change_pct": 52.4,
              "budget_type": "operating",
              "province": "ทั่วประเทศ",
              "plan_name": "แผนแม่บทภายใต้ยุทธศาสตร์ชาติ ประเด็นการพัฒนาศักยภาพคนตลอดช่วงชีวิต (สาธารณสุข)",
              "flags": [
                {
                  "rule": "unusual_increase",
                  "severity": "warning",
                  "label": "เพิ่มผิดปกติ",
                  "description": "งบประมาณเพิ่มขึ้น 52.4% จากปีก่อนหน้า ซึ่งเกินเกณฑ์ 50% ที่กำหนดไว้สำหรับการตรวจสอบเพิ่มเติม",
                  "statistical_context": {
                    "previous_avg_5yr": 1980000000,
                    "threshold_pct": 50
                  }
                }
              ],
              "history": [
                { "year": "2564", "amount": 1800000000 },
                { "year": "2565", "amount": 1900000000 },
                { "year": "2566", "amount": 2000000000 },
                { "year": "2567", "amount": 2100000000 },
                { "year": "2568", "amount": 3200000000 }
              ]
            },
            {
              "id": "moph-001-02",
              "name": "โครงการวัคซีนป้องกันโรคประจำปี",
              "amount": 5600000000,
              "previous_amount": 5450000000,
              "change_pct": 2.8,
              "budget_type": "operating",
              "province": "ทั่วประเทศ",
              "plan_name": "แผนแม่บทภายใต้ยุทธศาสตร์ชาติ ประเด็นการพัฒนาศักยภาพคนตลอดช่วงชีวิต (สาธารณสุข)",
              "flags": [],
              "history": [
                { "year": "2564", "amount": 5200000000 },
                { "year": "2565", "amount": 5300000000 },
                { "year": "2566", "amount": 5380000000 },
                { "year": "2567", "amount": 5450000000 },
                { "year": "2568", "amount": 5600000000 }
              ]
            },
            {
              "id": "moph-001-03",
              "name": "โครงการพัฒนาห้องปฏิบัติการอ้างอิงด้านสาธารณสุข",
              "amount": 780000000,
              "previous_amount": 0,
              "change_pct": 0,
              "budget_type": "investment",
              "province": "นนทบุรี",
              "plan_name": "แผนแม่บทภายใต้ยุทธศาสตร์ชาติ ประเด็นการพัฒนาศักยภาพคนตลอดช่วงชีวิต (สาธารณสุข)",
              "flags": [],
              "history": [
                { "year": "2568", "amount": 780000000 }
              ]
            }
          ]
        },
        {
          "id": "moph-002",
          "name": "กรมการแพทย์",
          "budget": 16950000000,
          "projects": [
            {
              "id": "moph-002-01",
              "name": "โครงการจัดซื้อเครื่องมือแพทย์ขั้นสูงสำหรับโรงพยาบาลศูนย์",
              "amount": 12400000000,
              "previous_amount": 4300000000,
              "change_pct": 188.4,
              "budget_type": "investment",
              "province": "กรุงเทพมหานคร",
              "plan_name": "แผนแม่บทภายใต้ยุทธศาสตร์ชาติ ประเด็นการพัฒนาศักยภาพคนตลอดช่วงชีวิต (สาธารณสุข)",
              "flags": [
                {
                  "rule": "unusual_increase",
                  "severity": "critical",
                  "label": "เพิ่มผิดปกติ",
                  "description": "งบประมาณเพิ่มขึ้น 188.4% จากปีก่อนหน้า (เกิน 100%) ถือเป็นความผิดปกติระดับวิกฤตที่ควรตรวจสอบโดยเร่งด่วน",
                  "statistical_context": {
                    "previous_avg_5yr": 3980000000,
                    "threshold_pct": 50
                  }
                },
                {
                  "rule": "statistical_outlier",
                  "severity": "critical",
                  "label": "มูลค่าสูงผิดปกติ",
                  "description": "มูลค่างบประมาณสูงกว่าค่าเฉลี่ยของหมวดหมู่งบลงทุนเกิน 3 เท่าของส่วนเบี่ยงเบนมาตรฐาน (SD) และเข้าเกณฑ์ตรวจพบ 2 กฎพร้อมกัน",
                  "statistical_context": {
                    "previous_avg_5yr": 3980000000,
                    "std_deviations": 3.6,
                    "category_avg_multiple": 4.1
                  }
                }
              ],
              "history": [
                { "year": "2564", "amount": 3600000000 },
                { "year": "2565", "amount": 3900000000 },
                { "year": "2566", "amount": 4100000000 },
                { "year": "2567", "amount": 4300000000 },
                { "year": "2568", "amount": 12400000000 }
              ]
            },
            {
              "id": "moph-002-02",
              "name": "โครงการพัฒนาระบบบริการสุขภาพปฐมภูมิ",
              "amount": 2900000000,
              "previous_amount": 2750000000,
              "change_pct": 5.5,
              "budget_type": "operating",
              "province": "ทั่วประเทศ",
              "plan_name": "แผนแม่บทภายใต้ยุทธศาสตร์ชาติ ประเด็นการพัฒนาศักยภาพคนตลอดช่วงชีวิต (สาธารณสุข)",
              "flags": [],
              "history": [
                { "year": "2564", "amount": 2500000000 },
                { "year": "2565", "amount": 2600000000 },
                { "year": "2566", "amount": 2680000000 },
                { "year": "2567", "amount": 2750000000 },
                { "year": "2568", "amount": 2900000000 }
              ]
            },
            {
              "id": "moph-002-03",
              "name": "โครงการกระจายบุคลากรทางการแพทย์สู่พื้นที่ชนบท",
              "amount": 1650000000,
              "previous_amount": 1580000000,
              "change_pct": 4.4,
              "budget_type": "personnel",
              "province": "สุรินทร์",
              "plan_name": "แผนแม่บทภายใต้ยุทธศาสตร์ชาติ ประเด็นการพัฒนาศักยภาพคนตลอดช่วงชีวิต (สาธารณสุข)",
              "flags": [],
              "history": [
                { "year": "2564", "amount": 1450000000 },
                { "year": "2565", "amount": 1500000000 },
                { "year": "2566", "amount": 1540000000 },
                { "year": "2567", "amount": 1580000000 },
                { "year": "2568", "amount": 1650000000 }
              ]
            }
          ]
        }
      ]
    },
    {
      "id": "mot",
      "name": "กระทรวงคมนาคม",
      "budget": 67645000000,
      "color_category": "amber",
      "departments": [
        {
          "id": "mot-001",
          "name": "กรมทางหลวง",
          "budget": 25020000000,
          "projects": [
            {
              "id": "mot-001-01",
              "name": "โครงการก่อสร้างทางหลวงพิเศษระหว่างเมือง",
              "amount": 18500000000,
              "previous_amount": 15200000000,
              "change_pct": 21.7,
              "budget_type": "investment",
              "province": "นครราชสีมา",
              "plan_name": "ยุทธศาสตร์ชาติด้านการสร้างความสามารถในการแข่งขัน",
              "flags": [],
              "history": [
                { "year": "2564", "amount": 12000000000 },
                { "year": "2565", "amount": 13200000000 },
                { "year": "2566", "amount": 14300000000 },
                { "year": "2567", "amount": 15200000000 },
                { "year": "2568", "amount": 18500000000 }
              ]
            },
            {
              "id": "mot-001-02",
              "name": "โครงการบำรุงรักษาทางหลวงทั่วประเทศ",
              "amount": 6200000000,
              "previous_amount": 6050000000,
              "change_pct": 2.5,
              "budget_type": "operating",
              "province": "ทั่วประเทศ",
              "plan_name": "ยุทธศาสตร์ชาติด้านการสร้างความสามารถในการแข่งขัน",
              "flags": [],
              "history": [
                { "year": "2564", "amount": 5800000000 },
                { "year": "2565", "amount": 5900000000 },
                { "year": "2566", "amount": 5980000000 },
                { "year": "2567", "amount": 6050000000 },
                { "year": "2568", "amount": 6200000000 }
              ]
            },
            {
              "id": "mot-001-03",
              "name": "โครงการศึกษาความเหมาะสมเส้นทางคมนาคมใหม่",
              "amount": 320000000,
              "previous_amount": 190000000,
              "change_pct": 68.4,
              "budget_type": "other",
              "province": "ภูเก็ต",
              "plan_name": "ยุทธศาสตร์ชาติด้านการสร้างความสามารถในการแข่งขัน",
              "flags": [
                {
                  "rule": "unusual_increase",
                  "severity": "warning",
                  "label": "เพิ่มผิดปกติ",
                  "description": "งบประมาณเพิ่มขึ้น 68.4% จากปีก่อนหน้า ซึ่งเกินเกณฑ์ 50% ที่กำหนดไว้สำหรับการตรวจสอบเพิ่มเติม",
                  "statistical_context": {
                    "previous_avg_5yr": 175000000,
                    "threshold_pct": 50
                  }
                }
              ],
              "history": [
                { "year": "2564", "amount": 160000000 },
                { "year": "2565", "amount": 170000000 },
                { "year": "2566", "amount": 180000000 },
                { "year": "2567", "amount": 190000000 },
                { "year": "2568", "amount": 320000000 }
              ]
            }
          ]
        },
        {
          "id": "mot-002",
          "name": "กรมการขนส่งทางราง",
          "budget": 42625000000,
          "projects": [
            {
              "id": "mot-002-01",
              "name": "โครงการรถไฟความเร็วสูงระยะที่ 2",
              "amount": 42000000000,
              "previous_amount": 38500000000,
              "change_pct": 9.1,
              "budget_type": "investment",
              "province": "นครราชสีมา",
              "plan_name": "ยุทธศาสตร์ชาติด้านการสร้างความสามารถในการแข่งขัน",
              "flags": [
                {
                  "rule": "statistical_outlier",
                  "severity": "warning",
                  "label": "มูลค่าสูงผิดปกติ",
                  "description": "มูลค่างบประมาณสูงกว่าค่าเฉลี่ยของโครงการในหมวดงบลงทุนเกิน 3 เท่าของส่วนเบี่ยงเบนมาตรฐาน (SD) — ควรพิจารณาความคุ้มค่าและระยะเวลาดำเนินการประกอบ",
                  "statistical_context": {
                    "previous_avg_5yr": 36800000000,
                    "std_deviations": 3.2,
                    "category_avg_multiple": 5.4
                  }
                }
              ],
              "history": [
                { "year": "2564", "amount": 30000000000 },
                { "year": "2565", "amount": 33500000000 },
                { "year": "2566", "amount": 36000000000 },
                { "year": "2567", "amount": 38500000000 },
                { "year": "2568", "amount": 42000000000 }
              ]
            },
            {
              "id": "mot-002-02",
              "name": "โครงการพัฒนาระบบจัดเก็บค่าโดยสารอัตโนมัติ",
              "amount": 540000000,
              "previous_amount": 510000000,
              "change_pct": 5.9,
              "budget_type": "operating",
              "province": "กรุงเทพมหานคร",
              "plan_name": "ยุทธศาสตร์ชาติด้านการสร้างความสามารถในการแข่งขัน",
              "flags": [],
              "history": [
                { "year": "2564", "amount": 470000000 },
                { "year": "2565", "amount": 485000000 },
                { "year": "2566", "amount": 498000000 },
                { "year": "2567", "amount": 510000000 },
                { "year": "2568", "amount": 540000000 }
              ]
            },
            {
              "id": "mot-002-03",
              "name": "โครงการอบรมบุคลากรระบบขนส่งทางราง",
              "amount": 85000000,
              "previous_amount": 80000000,
              "change_pct": 6.3,
              "budget_type": "personnel",
              "province": "ทั่วประเทศ",
              "plan_name": "ยุทธศาสตร์ชาติด้านการสร้างความสามารถในการแข่งขัน",
              "flags": [],
              "history": [
                { "year": "2564", "amount": 72000000 },
                { "year": "2565", "amount": 75000000 },
                { "year": "2566", "amount": 78000000 },
                { "year": "2567", "amount": 80000000 },
                { "year": "2568", "amount": 85000000 }
              ]
            }
          ]
        }
      ]
    },
    {
      "id": "moi",
      "name": "กระทรวงมหาดไทย",
      "budget": 6450000000,
      "color_category": "coral",
      "departments": [
        {
          "id": "moi-001",
          "name": "กรมการปกครอง",
          "budget": 4760000000,
          "projects": [
            {
              "id": "moi-001-01",
              "name": "โครงการพัฒนาระบบบัตรประจำตัวประชาชนดิจิทัล",
              "amount": 1950000000,
              "previous_amount": 1180000000,
              "change_pct": 65.3,
              "budget_type": "investment",
              "province": "ทั่วประเทศ",
              "plan_name": "ยุทธศาสตร์ชาติด้านการปรับสมดุลและพัฒนาระบบการบริหารจัดการภาครัฐ",
              "flags": [
                {
                  "rule": "unusual_increase",
                  "severity": "warning",
                  "label": "เพิ่มผิดปกติ",
                  "description": "งบประมาณเพิ่มขึ้น 65.3% จากปีก่อนหน้า ซึ่งเกินเกณฑ์ 50% ที่กำหนดไว้สำหรับการตรวจสอบเพิ่มเติม",
                  "statistical_context": {
                    "previous_avg_5yr": 1135000000,
                    "threshold_pct": 50
                  }
                }
              ],
              "history": [
                { "year": "2564", "amount": 850000000 },
                { "year": "2565", "amount": 980000000 },
                { "year": "2566", "amount": 1080000000 },
                { "year": "2567", "amount": 1180000000 },
                { "year": "2568", "amount": 1950000000 }
              ]
            },
            {
              "id": "moi-001-02",
              "name": "โครงการสนับสนุนการเลือกตั้งท้องถิ่น",
              "amount": 2400000000,
              "previous_amount": 2350000000,
              "change_pct": 2.1,
              "budget_type": "operating",
              "province": "ทั่วประเทศ",
              "plan_name": "ยุทธศาสตร์ชาติด้านการปรับสมดุลและพัฒนาระบบการบริหารจัดการภาครัฐ",
              "flags": [],
              "history": [
                { "year": "2564", "amount": 2200000000 },
                { "year": "2565", "amount": 2250000000 },
                { "year": "2566", "amount": 2300000000 },
                { "year": "2567", "amount": 2350000000 },
                { "year": "2568", "amount": 2400000000 }
              ]
            },
            {
              "id": "moi-001-03",
              "name": "โครงการพัฒนาระบบฐานข้อมูลทะเบียนราษฎร",
              "amount": 410000000,
              "previous_amount": 395000000,
              "change_pct": 3.8,
              "budget_type": "other",
              "province": "ทั่วประเทศ",
              "plan_name": "ยุทธศาสตร์ชาติด้านการปรับสมดุลและพัฒนาระบบการบริหารจัดการภาครัฐ",
              "flags": [],
              "history": [
                { "year": "2564", "amount": 370000000 },
                { "year": "2565", "amount": 380000000 },
                { "year": "2566", "amount": 388000000 },
                { "year": "2567", "amount": 395000000 },
                { "year": "2568", "amount": 410000000 }
              ]
            }
          ]
        },
        {
          "id": "moi-002",
          "name": "กรมป้องกันและบรรเทาสาธารณภัย",
          "budget": 1690000000,
          "projects": [
            {
              "id": "moi-002-01",
              "name": "โครงการจัดซื้ออุปกรณ์กู้ภัยและดับเพลิงประจำภูมิภาค",
              "amount": 890000000,
              "previous_amount": 540000000,
              "change_pct": 64.8,
              "budget_type": "investment",
              "province": "เชียงราย",
              "plan_name": "ยุทธศาสตร์ชาติด้านการปรับสมดุลและพัฒนาระบบการบริหารจัดการภาครัฐ",
              "flags": [
                {
                  "rule": "unusual_increase",
                  "severity": "warning",
                  "label": "เพิ่มผิดปกติ",
                  "description": "งบประมาณเพิ่มขึ้น 64.8% จากปีก่อนหน้า ซึ่งเกินเกณฑ์ 50% ที่กำหนดไว้สำหรับการตรวจสอบเพิ่มเติม",
                  "statistical_context": {
                    "previous_avg_5yr": 495000000,
                    "threshold_pct": 50
                  }
                }
              ],
              "history": [
                { "year": "2564", "amount": 420000000 },
                { "year": "2565", "amount": 470000000 },
                { "year": "2566", "amount": 505000000 },
                { "year": "2567", "amount": 540000000 },
                { "year": "2568", "amount": 890000000 }
              ]
            },
            {
              "id": "moi-002-02",
              "name": "โครงการพัฒนาระบบเตือนภัยพิบัติล่วงหน้า",
              "amount": 620000000,
              "previous_amount": 0,
              "change_pct": 0,
              "budget_type": "other",
              "province": "ทั่วประเทศ",
              "plan_name": "ยุทธศาสตร์ชาติด้านการปรับสมดุลและพัฒนาระบบการบริหารจัดการภาครัฐ",
              "flags": [],
              "history": [
                { "year": "2568", "amount": 620000000 }
              ]
            },
            {
              "id": "moi-002-03",
              "name": "โครงการฝึกอบรมอาสาสมัครป้องกันภัยฝ่ายพลเรือน",
              "amount": 180000000,
              "previous_amount": 172000000,
              "change_pct": 4.7,
              "budget_type": "personnel",
              "province": "ทั่วประเทศ",
              "plan_name": "ยุทธศาสตร์ชาติด้านการปรับสมดุลและพัฒนาระบบการบริหารจัดการภาครัฐ",
              "flags": [],
              "history": [
                { "year": "2564", "amount": 160000000 },
                { "year": "2565", "amount": 165000000 },
                { "year": "2566", "amount": 168000000 },
                { "year": "2567", "amount": 172000000 },
                { "year": "2568", "amount": 180000000 }
              ]
            }
          ]
        }
      ]
    },
    {
      "id": "moac",
      "name": "กระทรวงเกษตรและสหกรณ์",
      "budget": 27260000000,
      "color_category": "teal",
      "departments": [
        {
          "id": "moac-001",
          "name": "กรมชลประทาน",
          "budget": 12290000000,
          "projects": [
            {
              "id": "moac-001-01",
              "name": "โครงการพัฒนาแหล่งน้ำชลประทานขนาดใหญ่",
              "amount": 9800000000,
              "previous_amount": 9400000000,
              "change_pct": 4.3,
              "budget_type": "investment",
              "province": "พิษณุโลก",
              "plan_name": "ยุทธศาสตร์ชาติด้านการสร้างการเติบโตบนคุณภาพชีวิตที่เป็นมิตรต่อสิ่งแวดล้อม",
              "flags": [],
              "history": [
                { "year": "2564", "amount": 8800000000 },
                { "year": "2565", "amount": 9000000000 },
                { "year": "2566", "amount": 9200000000 },
                { "year": "2567", "amount": 9400000000 },
                { "year": "2568", "amount": 9800000000 }
              ]
            },
            {
              "id": "moac-001-02",
              "name": "โครงการซ่อมบำรุงระบบชลประทานทั่วประเทศ",
              "amount": 2150000000,
              "previous_amount": 1320000000,
              "change_pct": 62.9,
              "budget_type": "operating",
              "province": "ทั่วประเทศ",
              "plan_name": "ยุทธศาสตร์ชาติด้านการสร้างการเติบโตบนคุณภาพชีวิตที่เป็นมิตรต่อสิ่งแวดล้อม",
              "flags": [
                {
                  "rule": "unusual_increase",
                  "severity": "warning",
                  "label": "เพิ่มผิดปกติ",
                  "description": "งบประมาณเพิ่มขึ้น 62.9% จากปีก่อนหน้า ซึ่งเกินเกณฑ์ 50% ที่กำหนดไว้สำหรับการตรวจสอบเพิ่มเติม",
                  "statistical_context": {
                    "previous_avg_5yr": 1330000000,
                    "threshold_pct": 50
                  }
                }
              ],
              "history": [
                { "year": "2564", "amount": 1050000000 },
                { "year": "2565", "amount": 1150000000 },
                { "year": "2566", "amount": 1230000000 },
                { "year": "2567", "amount": 1320000000 },
                { "year": "2568", "amount": 2150000000 }
              ]
            },
            {
              "id": "moac-001-03",
              "name": "โครงการบริหารจัดการน้ำโดยชุมชน",
              "amount": 340000000,
              "previous_amount": 325000000,
              "change_pct": 4.6,
              "budget_type": "other",
              "province": "อุบลราชธานี",
              "plan_name": "ยุทธศาสตร์ชาติด้านการสร้างการเติบโตบนคุณภาพชีวิตที่เป็นมิตรต่อสิ่งแวดล้อม",
              "flags": [],
              "history": [
                { "year": "2564", "amount": 300000000 },
                { "year": "2565", "amount": 310000000 },
                { "year": "2566", "amount": 318000000 },
                { "year": "2567", "amount": 325000000 },
                { "year": "2568", "amount": 340000000 }
              ]
            }
          ]
        },
        {
          "id": "moac-002",
          "name": "กรมส่งเสริมการเกษตร",
          "budget": 14970000000,
          "projects": [
            {
              "id": "moac-002-01",
              "name": "โครงการประกันรายได้เกษตรกรผู้ปลูกพืชเศรษฐกิจ",
              "amount": 14200000000,
              "previous_amount": 13900000000,
              "change_pct": 2.2,
              "budget_type": "operating",
              "province": "ทั่วประเทศ",
              "plan_name": "ยุทธศาสตร์ชาติด้านการสร้างการเติบโตบนคุณภาพชีวิตที่เป็นมิตรต่อสิ่งแวดล้อม",
              "flags": [
                {
                  "rule": "statistical_outlier",
                  "severity": "warning",
                  "label": "มูลค่าสูงผิดปกติ",
                  "description": "มูลค่างบประมาณสูงกว่าค่าเฉลี่ยของโครงการในหมวดงบดำเนินงานเกิน 3 เท่าของส่วนเบี่ยงเบนมาตรฐาน (SD)",
                  "statistical_context": {
                    "previous_avg_5yr": 13730000000,
                    "std_deviations": 3.1,
                    "category_avg_multiple": 3.8
                  }
                }
              ],
              "history": [
                { "year": "2564", "amount": 13200000000 },
                { "year": "2565", "amount": 13450000000 },
                { "year": "2566", "amount": 13650000000 },
                { "year": "2567", "amount": 13900000000 },
                { "year": "2568", "amount": 14200000000 }
              ]
            },
            {
              "id": "moac-002-02",
              "name": "โครงการส่งเสริมเกษตรอินทรีย์และเกษตรปลอดภัย",
              "amount": 560000000,
              "previous_amount": 410000000,
              "change_pct": 36.6,
              "budget_type": "other",
              "province": "เชียงใหม่",
              "plan_name": "ยุทธศาสตร์ชาติด้านการสร้างการเติบโตบนคุณภาพชีวิตที่เป็นมิตรต่อสิ่งแวดล้อม",
              "flags": [],
              "history": [
                { "year": "2564", "amount": 340000000 },
                { "year": "2565", "amount": 365000000 },
                { "year": "2566", "amount": 388000000 },
                { "year": "2567", "amount": 410000000 },
                { "year": "2568", "amount": 560000000 }
              ]
            },
            {
              "id": "moac-002-03",
              "name": "โครงการพัฒนาเกษตรกรรุ่นใหม่ (Smart Farmer)",
              "amount": 210000000,
              "previous_amount": 0,
              "change_pct": 0,
              "budget_type": "personnel",
              "province": "ทั่วประเทศ",
              "plan_name": "ยุทธศาสตร์ชาติด้านการสร้างการเติบโตบนคุณภาพชีวิตที่เป็นมิตรต่อสิ่งแวดล้อม",
              "flags": [],
              "history": [
                { "year": "2568", "amount": 210000000 }
              ]
            }
          ]
        }
      ]
    }
  ]
}
